colab_sshfs/__init__.py
colab_sshfs/colab_sshfs.py
colab_sshfs-0.0.7.dist-info/LICENSE
colab_sshfs-0.0.7.dist-info/METADATA
colab_sshfs-0.0.7.dist-info/WHEEL
colab_sshfs-0.0.7.dist-info/top_level.txt
colab_sshfs-0.0.7.dist-info/RECORD
