Metadata-Version: 2.1
Name: colab-sshfs
Version: 0.0.7
Summary: Mount sshfs remotes on Google Colaboratory
Home-page: https://github.com/bil/colab-sshfs
Author: Paul Nuyujukian
License: GPL2
Platform: UNKNOWN
License-File: LICENSE
